{
  "entity.beast.ambient": {
    "sounds": [
      "mr:entity/beast/ambient1",
      "mr:entity/beast/ambient2",
      "mr:entity/beast/ambient3"
    ],
    "subtitle": "subtitles.entity.mrbeast.ambient"
  },
  "entity.beast.death": {
    "sounds": [
      "mr:entity/beast/death1",
      "mr:entity/beast/death2",
      "mr:entity/beast/death3",
      "mr:entity/beast/death4",
      "mr:entity/beast/death5",
      "mr:entity/beast/death6",
      "mr:entity/beast/death7",
      "mr:entity/beast/death8"
    ],
    "subtitle": "subtitles.entity.mrbeast.death"
  },
  "entity.beast.hurt": {
    "sounds": [
      "mr:entity/beast/hurt"
    ],
    "subtitle": "subtitles.entity.mrbeast.hurt"
  },
  "entity.beast.spawn": {
    "sounds": [
      "mr:entity/beast/spawn"
    ],
    "subtitle": "subtitles.entity.mrbeast.spawn"
  },
  "entity.beast.step": {
    "sounds": [
      "mr:entity/beast/step1",
      "mr:entity/beast/step2",
      "mr:entity/beast/step3",
      "mr:entity/beast/step4",
      "mr:entity/beast/step5",
      "mr:entity/beast/step6",
      "mr:entity/beast/step7"
    ],
    "subtitle": "subtitles.entity.mrbeast.step"
  }
}
